markdown_svgbob/__init__.py
markdown_svgbob/__main__.py
markdown_svgbob/extension.py
markdown_svgbob/wrapper.py
markdown_svgbob/bin/svgbob_0.5.5_x86_64-Darwin
markdown_svgbob/bin/svgbob_0.5.5_x86_64-Linux
markdown_svgbob/bin/svgbob_0.5.5_x86_64-Windows.exe
markdown_svgbob-202406.1023.dist-info/LICENSE
markdown_svgbob-202406.1023.dist-info/METADATA
markdown_svgbob-202406.1023.dist-info/WHEEL
markdown_svgbob-202406.1023.dist-info/entry_points.txt
markdown_svgbob-202406.1023.dist-info/top_level.txt
markdown_svgbob-202406.1023.dist-info/zip-safe
markdown_svgbob-202406.1023.dist-info/RECORD
